Task_2/Quetion_1/fsm11x.v
module fsm11x (input in,clk,reset,output reg out);

parameter A =2'b00,B=2'b01,C=2'b10 ;

reg [1:0] present,next ;
    
always @(posedge clk or posedge reset) begin
     if (reset) begin
        present<=A;
     end else begin
        present<=next;
     end
     
end

always @(in,present) begin
  case (present)
    A: begin
      next =in? B:A;
      out = 0;
    end 
    B: begin
      next = in?C:A;
      out = 0;
    end 
    C: begin
      next = in?A:A;
      out = 1;
    end 
    default: begin
      next = A;
      out = 0;
    end
  endcase
end

endmodule

Task_2/Quetion_1/fsm011.v
module fsm011 (input in,clk,reset,output reg out);

parameter A =2'b00,B=2'b01,C=2'b10 ;

reg [1:0] present,next ;
    
always @(posedge clk or posedge reset) begin
     if (reset) begin
        present<=A;
     end else begin
        present<=next;
     end
     
end

always @(in,present) begin
  case (present)
    A: begin
      next =in? A:B;
      out = 0;
    end 
    B: begin
      next = in?C:B;
      out = 0;
    end 
    C: begin
      next = in?A:B;
      out = in?1:0;
    end 
    default: begin
      next = A;
      out = 0;
    end
  endcase
end

endmodule

Task_2/Quetion_1/fsm101.v
module fsm101 (input in,clk,reset,output reg out);

parameter A =2'b00,B=2'b01,C=2'b10 ;

reg [1:0] present,next ;
    
always @(posedge clk or posedge reset) begin
     if (reset) begin
        present<=A;
     end else begin
        present<=next;
     end
     
end

always @(in,present) begin
  case (present)
    A: begin
      next =in? B:A;
      out = 0;
    end 
    B: begin
      next = in?B:C;
      out = 0;
    end 
    C: begin
      next = in?B:A;
      out = in?1:0;
    end 
    default: begin
      next = A;
      out = 0;
    end
  endcase
end

endmodule

Task_2/Quetion_1/fsmcomb.v
`include "fsm011.v"
`include "fsm101.v"
`include "fsm11x.v"


module fsmcomb (input in,clk,reset,output reg out);

// parameter A =2'b00,B=2'b01,C=2'b10 ;

// reg [1:0] present,next ;
    
// always @(posedge clk or posedge reset) begin
//      if (reset) begin
//         present<=A;
//      end else begin
//         present<=next;
//      end
     
// end

// always @(in,present) begin
//   case (present)
//     A: begin
//       next =in? B:A;
//       out = 0;
//     end 
//     B: begin
//       next = in?B:C;
//       out = in?1:0;
//     end 
//     C: begin
//       next = in?C:B;
//       out = in?1:0;
//     end 
//     default: begin
//       next = A;
//       out = 0;
//     end
//   endcase
// end
wire out1,out2,out3;

fsm101 g101 (.in(in),.clk(clk),.reset(reset),.out(out1));
fsm011 g011 (.in(in),.clk(clk),.reset(reset),.out(out2));
fsm11x g11x (.in(in),.clk(clk),.reset(reset),.out(out3));

always @(posedge clk or negedge clk ) begin
    if (reset) begin
        out<=0;
    end else begin
        out = out1 | out2 | out3 ;
    end
end

endmodule

Task_2/Quetion_1/fsmcomb_tb.v
module fsmcomb_tb;
     reg in, clk, reset;       // Declare testbench signals
    wire out;         // Declare output signal

    // Instantiate the DUT (Device Under Test)
  fsmcomb dut (
        .in(in),
        .clk(clk),
        .reset(reset),
        .out(out)
    );

    // Clock generation: 10 ns period
    always #5 clk = ~clk;

    // Test sequence
    initial begin
        $dumpfile("fsm.vcd");     // Specify dump file for waveform
        $dumpvars(0, fsmcomb_tb);
        // Initialize signals
        clk = 0; 
        reset = 1; 
        in = 0;

        // Apply reset
        #10 reset = 0;

        // Apply input sequence
        #10 in = 0;
        #10 in = 1;
        #10 in = 0;
        #10 in = 1;
        #10 in = 0;
        #10 in = 1;
        #10 in = 1;
        #10 in = 0;
        #10 in = 0;
        #10 in = 1;
        #10;
        in=0;

        #20 $finish; // End simulation
    end
endmodule

Task_2/Quetion_1/fsm.vcd
$date
	Tue Jan 21 23:50:12 2025
$end
$version
	Icarus Verilog
$end
$timescale
	1s
$end
$scope module fsmcomb_tb $end
$var wire 1 ! out $end
$var reg 1 " clk $end
$var reg 1 # in $end
$var reg 1 $ reset $end
$scope module dut $end
$var wire 1 " clk $end
$var wire 1 # in $end
$var wire 1 $ reset $end
$var wire 1 % out3 $end
$var wire 1 & out2 $end
$var wire 1 ' out1 $end
$var reg 1 ! out $end
$scope module g011 $end
$var wire 1 " clk $end
$var wire 1 # in $end
$var wire 1 $ reset $end
$var parameter 2 ( A $end
$var parameter 2 ) B $end
$var parameter 2 * C $end
$var reg 2 + next [1:0] $end
$var reg 1 & out $end
$var reg 2 , present [1:0] $end
$upscope $end
$scope module g101 $end
$var wire 1 " clk $end
$var wire 1 # in $end
$var wire 1 $ reset $end
$var parameter 2 - A $end
$var parameter 2 . B $end
$var parameter 2 / C $end
$var reg 2 0 next [1:0] $end
$var reg 1 ' out $end
$var reg 2 1 present [1:0] $end
$upscope $end
$scope module g11x $end
$var wire 1 " clk $end
$var wire 1 # in $end
$var wire 1 $ reset $end
$var parameter 2 2 A $end
$var parameter 2 3 B $end
$var parameter 2 4 C $end
$var reg 2 5 next [1:0] $end
$var reg 1 % out $end
$var reg 2 6 present [1:0] $end
$upscope $end
$upscope $end
$upscope $end
$enddefinitions $end
$comment Show the parameter values. $end
$dumpall
b10 4
b1 3
b0 2
b10 /
b1 .
b0 -
b10 *
b1 )
b0 (
$end
#0
$dumpvars
b0 6
b0 5
b0 1
b0 0
b0 ,
b1 +
0'
0&
0%
1$
0#
0"
0!
$end
#5
1"
#10
0"
0$
#15
b1 ,
1"
#20
0"
#25
1"
#30
b10 +
b1 0
b1 5
0"
1#
#35
1&
b0 +
b10 5
b1 1
b10 ,
b1 6
1"
#40
0&
b1 +
b10 0
b0 5
0"
0#
#45
b0 0
b0 6
b1 ,
b10 1
1"
#50
1!
b10 +
1'
b1 0
b1 5
0"
1#
#55
0'
1&
b0 +
b10 5
b1 1
b10 ,
b1 6
1"
#60
0!
0&
b1 +
b10 0
b0 5
0"
0#
#65
b0 0
b0 6
b1 ,
b10 1
1"
#70
1!
b10 +
1'
b1 0
b1 5
0"
1#
#75
0'
1&
b0 +
b10 5
b1 1
b10 ,
b1 6
1"
#80
0"
#85
1%
b0 5
0&
b10 6
b0 ,
1"
#90
b1 +
b10 0
0"
0#
#95
b0 0
0%
b10 1
b1 ,
b0 6
1"
#100
0!
0"
#105
b0 1
1"
#110
b10 +
b1 0
b1 5
0"
1#
#115
1&
b0 +
b10 5
b1 1
b10 ,
b1 6
1"
#120
0&
b1 +
b10 0
b0 5
0"
0#
#125
b0 0
b0 6
b1 ,
b10 1
1"
#130
0"
#135
b0 1
1"
